libraries/__init__.py
libraries/click/__init__.py
libraries/click/_bashcomplete.py
libraries/click/_compat.py
libraries/click/_termui_impl.py
libraries/click/_textwrap.py
libraries/click/_unicodefun.py
libraries/click/_winconsole.py
libraries/click/core.py
libraries/click/decorators.py
libraries/click/exceptions.py
libraries/click/formatting.py
libraries/click/globals.py
libraries/click/parser.py
libraries/click/termui.py
libraries/click/testing.py
libraries/click/types.py
libraries/click/utils.py
setonix/__init__.py
tests/__init__.py
tests/test_setonix.py
SETONIX-0.42.11.dist-info/METADATA
SETONIX-0.42.11.dist-info/WHEEL
SETONIX-0.42.11.dist-info/top_level.txt
SETONIX-0.42.11.dist-info/RECORD
