Metadata-Version: 2.1
Name: SETONIX
Version: 0.42.11
Summary: TBA
Home-page: https://github.com/scott91e1
Author: Scott McCallum (github.com scott91e1)
Author-email: 262464@195387.com
License: UNKNOWN
Platform: UNKNOWN
Classifier: Programming Language :: Python :: 3
Classifier: License :: OSI Approved :: MIT License
Classifier: Operating System :: OS Independent
Requires-Python: >=3.6
